{
  "main": {
    "id": "b85fce2869bb54b3",
    "type": "split",
    "children": [
      {
        "id": "6b3f8752e27046be",
        "type": "tabs",
        "children": [
          {
            "id": "d64c7076c06c675c",
            "type": "leaf",
            "state": {
              "type": "markdown",
              "state": {
                "file": "Linux/Linux Basico.md",
                "mode": "source",
                "source": false
              }
            }
          },
          {
            "id": "50589c328efc7283",
            "type": "leaf",
            "state": {
              "type": "markdown",
              "state": {
                "file": "Docker/Docker file.md",
                "mode": "source",
                "source": false
              }
            }
          }
        ]
      }
    ],
    "direction": "vertical"
  },
  "left": {
    "id": "adfb21087bea0655",
    "type": "split",
    "children": [
      {
        "id": "97997bcff31b112b",
        "type": "tabs",
        "children": [
          {
            "id": "9c1d809fb11d0ac2",
            "type": "leaf",
            "state": {
              "type": "file-explorer",
              "state": {
                "sortOrder": "alphabetical"
              }
            }
          },
          {
            "id": "a3ca4eed9e14fe24",
            "type": "leaf",
            "state": {
              "type": "search",
              "state": {
                "query": "sqli",
                "matchingCase": false,
                "explainSearch": false,
                "collapseAll": false,
                "extraContext": false,
                "sortOrder": "alphabetical"
              }
            }
          },
          {
            "id": "3728582bbd9c1fc3",
            "type": "leaf",
            "state": {
              "type": "bookmarks",
              "state": {}
            }
          }
        ]
      }
    ],
    "direction": "horizontal",
    "width": 300
  },
  "right": {
    "id": "325cc5529e6cbb6a",
    "type": "split",
    "children": [
      {
        "id": "c80633956cafd4c6",
        "type": "tabs",
        "children": [
          {
            "id": "ee777ae560b3dff3",
            "type": "leaf",
            "state": {
              "type": "backlink",
              "state": {
                "file": "Linux/Linux Basico.md",
                "collapseAll": false,
                "extraContext": false,
                "sortOrder": "alphabetical",
                "showSearch": false,
                "searchQuery": "",
                "backlinkCollapsed": false,
                "unlinkedCollapsed": true
              }
            }
          },
          {
            "id": "0d903626249147ae",
            "type": "leaf",
            "state": {
              "type": "outgoing-link",
              "state": {
                "file": "Linux/Linux Basico.md",
                "linksCollapsed": false,
                "unlinkedCollapsed": true
              }
            }
          },
          {
            "id": "42287682d2274037",
            "type": "leaf",
            "state": {
              "type": "tag",
              "state": {
                "sortOrder": "frequency",
                "useHierarchy": true
              }
            }
          },
          {
            "id": "adb1b70a9e3ae4d3",
            "type": "leaf",
            "state": {
              "type": "outline",
              "state": {
                "file": "Linux/Linux Basico.md"
              }
            }
          }
        ]
      }
    ],
    "direction": "horizontal",
    "width": 300,
    "collapsed": true
  },
  "left-ribbon": {
    "hiddenItems": {
      "switcher:Abrir selector r치pido": false,
      "graph:Abrir vista gr치fica": false,
      "canvas:Crear nuevo lienzo": false,
      "daily-notes:Abrir la nota de hoy": false,
      "templates:Insertar plantilla": false,
      "command-palette:Abrir paleta de comandos": false,
      "markdown-importer:Abrir el importador de Markdown": false,
      "random-note:Abrir nota al azar": false,
      "audio-recorder:Iniciar/Detener la grabaci칩n": false,
      "workspaces:Gestionar disposiciones de espacio de trabajo": false
    }
  },
  "active": "d64c7076c06c675c",
  "lastOpenFiles": [
    "游깷Ciberseguridad/Wifi Wireless/Wireless.md",
    "游깷Ciberseguridad/Wifi Wireless",
    "游깷Ciberseguridad/Certificaciones/Titulos obtenidos/certificado-preparacion-para-la-certificacion-del-ejptv2.pdf",
    "游깷Ciberseguridad/Certificaciones/Titulos obtenidos/certificado-gestion-de-conocimiento-con-obsidian.pdf",
    "游깷Ciberseguridad/Certificaciones/Titulos obtenidos",
    "游깷Ciberseguridad/Certificaciones/Certificaciones.md",
    "游깷Ciberseguridad/Certificaciones",
    "游깷Ciberseguridad/PIVOTING/Pivoting Windows/Pivoting en una maquina Windows.md",
    "游깷Ciberseguridad/PIVOTING/Representaci칩n de la red.md",
    "游깷Ciberseguridad/PIVOTING/Pivoting Windows",
    "游깷Ciberseguridad/PIVOTING/Mapa de Red.canvas",
    "游깷Ciberseguridad/PIVOTING",
    "游깷Ciberseguridad/Puertos y Servicios/Puerto 80  - 443(TCP) Web/Wordpress.md",
    "游깷Ciberseguridad/Puertos y Servicios/Puerto 80  - 443(TCP) Web/Puerto 80,443 - Http- Https Servicio Web.md",
    "游깷Ciberseguridad/Puertos y Servicios/Puerto 80  - 443(TCP) Web/Puerto 443 Https.md",
    "游깷Ciberseguridad/Puertos y Servicios/Puerto 80  - 443(TCP) Web/Prestashop.md",
    "游깷Ciberseguridad/Puertos y Servicios/Puerto 80  - 443(TCP) Web/Magento.md",
    "游깷Ciberseguridad/Puertos y Servicios/Puerto 80  - 443(TCP) Web/Joomla.md",
    "游깷Ciberseguridad/Puertos y Servicios/Puerto 80  - 443(TCP) Web/Drupal.md",
    "游깷Ciberseguridad/Puertos y Servicios/Puerto 80  - 443(TCP) Web/CMS Hub.md",
    "游깷Ciberseguridad/Puertos y Servicios/Puerto 80  - 443(TCP) Web",
    "游깷Ciberseguridad/Puertos y Servicios/Puerto 53 - DNS (TCP).md",
    "游깷Ciberseguridad/Puertos y Servicios/Puerto 445 SMB - SAMBA.md",
    "游깷Ciberseguridad/Puertos y Servicios/Puerto 3306  - Mysql (TCP).md",
    "游깷Ciberseguridad/Puertos y Servicios/Puerto 23 - TELNET   (TCP).md",
    "游깷Ciberseguridad/Puertos y Servicios/Puerto 22 SSH - SFTP (TCP).md",
    "游깷Ciberseguridad/Puertos y Servicios/Puerto 21 - FTP (TCP).md",
    "游깷Ciberseguridad/Puertos y Servicios/puerto 161 - SNMP (UDP).md",
    "游깷Ciberseguridad/Puertos y Servicios",
    "游깷Ciberseguridad/Tratamiento de la TTY.md",
    "游깷Ciberseguridad/Webs Interesantes.md",
    "游깷Ciberseguridad/Pantallazos/WPScann/WP-Scann API KEY.png",
    "游깷Ciberseguridad/Pantallazos/Wireless/Wifite result 1.png",
    "游깷Ciberseguridad/Pantallazos/Wireless/Wifite - primera pantalla.png",
    "游깷Ciberseguridad/Pantallazos/Tomcat/Tomcat - Web por defecto manager de Tomcat.png",
    "游깷Ciberseguridad/Pantallazos/Tomcat/Tomcat - Web por defecto de Tomcat.png",
    "游깷Ciberseguridad/Pantallazos/Tomcat/Tomcat - WAR file to deploy.png",
    "游깷Ciberseguridad/Pantallazos/Tomcat/Tomcat - payloads generate.png",
    "游깷Ciberseguridad/Pantallazos/Tomcat/Tomcat - pagina cancel default credentials.png",
    "游깷Ciberseguridad/Pantallazos/Tomcat/Tomcat - Conexion.png",
    "游깷Ciberseguridad/Pantallazos/Tomcat/Tomcat - Files uploaded.png",
    "游깷Ciberseguridad/Pantallazos/WPScann",
    "游깷Ciberseguridad/Herramientas - Tools/Steganografia/stegseek.md",
    "游깷Ciberseguridad/Herramientas - Tools/Steganografia/Steghide.md",
    "游깷Ciberseguridad/Herramientas - Tools/Herramientas profesionales SOC/wfuzz.md",
    "游깷Ciberseguridad/Herramientas - Tools/Herramientas profesionales SOC/EDR.md",
    "游깷Ciberseguridad/Herramientas - Tools/WPSeku (Wordpress).md",
    "Sin t칤tulo.canvas",
    "Ciberseguridad/PIVOTING/Mapa de Red.canvas"
  ]
}